{
  "profilePicture": [],
  "iEat": [],
  "skillsAndInterests": [],
  "gender": "male",
  "id": 17,
  "mail": "spam@lasse-nielsen.de",
  "firstname": "lasse",
  "lastname": "nielsen",
  "nickname": "unewochialat",
  "birthDate": "1990-07-01",
  "aboutme": "hey hier ist lasse",
  "street": "teststreet",
  "postcode": "13245",
  "town": "towntow",
  "region": "hessen",
  "country": "Germany",
  "languages": null,
  "phone": "123456789",
  "passId": "123445",
  "ispassport": false,
  "issuedOn": null,
  "expiresOn": "2020-10-20",
  "nationality": null,
  "schengenvisa": false,
  "visaexpiry": true,
  "visainvitation": false,
  "website": "lasse-nielsen.de",
  "emergencyContact": "em cont",
  "emergencyContactPhone": "123",
  "skillsAndInterestsDetails": "skills details",
  "expieriencesRelated": "related",
  "linkToExample": "google.com",
  "foodRequirements": null,
  "showMyProfile": null,
  "showMyMail": null,
  "showMyName": null,
  "showMyPhone": null,
  "showMyAddress": null,
  "medicalRequirements": null,
  "showNotOnLists": false,
  "userId": {
    "target_id": "6"
  }
}